anypoint/__init__.py
anypoint/anypoint.py
anypoint/authentication.py
anypoint/constants.py
anypoint/utils.py
anypoint/api/__init__.py
anypoint/api/api_manager.py
anypoint/api/application.py
anypoint/api/environment.py
anypoint/api/monitoring.py
anypoint/api/mq.py
anypoint/api/organization.py
anypoint/api/v2/__init__.py
anypoint/api/v2/application.py
anypoint/http_client/__init__.py
anypoint/http_client/client.py
anypoint/models/__init__.py
anypoint/models/api.py
anypoint/models/application.py
anypoint/models/destination.py
anypoint/models/environment.py
anypoint/models/organization.py
anypoint/models/private_space.py
anypoint/models/stats.py
anypoint/models/worker.py
anypoint-0.16.0.dist-info/licenses/LICENSE
anypoint-0.16.0.dist-info/WHEEL
anypoint-0.16.0.dist-info/METADATA
anypoint-0.16.0.dist-info/RECORD
