Metadata-Version: 2.4
Name: anypoint
Version: 0.16.0
Summary: anypoint, a python api client for the mulesoft anypoint APIs
Author-email: dlopes7 <davidribeirolopes@gmail.com>
Classifier: License :: OSI Approved :: MIT License
License-File: LICENSE
Requires-Dist: requests>=2.28.1
Project-URL: Home, https://github.com/dlopes7/anypoint-api-python-client
